data_analyser/__init__.py
data_analyser/compare_reports.py
data_analyser/config.py
data_analyser/config_default.yaml
data_analyser/config_minimal.yaml
data_analyser/expectations_report.py
data_analyser/profile_report.py
data_analyser/serialize_report.py
data_analyser/version.py
data_analyser/controller/__init__.py
data_analyser/controller/console.py
data_analyser/controller/pandas_decorator.py
data_analyser/model/__init__.py
data_analyser/model/alerts.py
data_analyser/model/correlations.py
data_analyser/model/dataframe.py
data_analyser/model/describe.py
data_analyser/model/description.py
data_analyser/model/duplicates.py
data_analyser/model/expectation_algorithms.py
data_analyser/model/handler.py
data_analyser/model/missing.py
data_analyser/model/pairwise.py
data_analyser/model/sample.py
data_analyser/model/summarizer.py
data_analyser/model/summary.py
data_analyser/model/summary_algorithms.py
data_analyser/model/table.py
data_analyser/model/timeseries_index.py
data_analyser/model/typeset.py
data_analyser/model/typeset_relations.py
data_analyser/model/pandas/__init__.py
data_analyser/model/pandas/correlations_pandas.py
data_analyser/model/pandas/dataframe_pandas.py
data_analyser/model/pandas/describe_boolean_pandas.py
data_analyser/model/pandas/describe_categorical_pandas.py
data_analyser/model/pandas/describe_counts_pandas.py
data_analyser/model/pandas/describe_date_pandas.py
data_analyser/model/pandas/describe_file_pandas.py
data_analyser/model/pandas/describe_generic_pandas.py
data_analyser/model/pandas/describe_image_pandas.py
data_analyser/model/pandas/describe_numeric_pandas.py
data_analyser/model/pandas/describe_path_pandas.py
data_analyser/model/pandas/describe_supported_pandas.py
data_analyser/model/pandas/describe_text_pandas.py
data_analyser/model/pandas/describe_timeseries_pandas.py
data_analyser/model/pandas/describe_url_pandas.py
data_analyser/model/pandas/discretize_pandas.py
data_analyser/model/pandas/duplicates_pandas.py
leo_data_analyser-1.0.0.dist-info/LICENSE
leo_data_analyser-1.0.0.dist-info/METADATA
leo_data_analyser-1.0.0.dist-info/WHEEL
leo_data_analyser-1.0.0.dist-info/entry_points.txt
leo_data_analyser-1.0.0.dist-info/top_level.txt
leo_data_analyser-1.0.0.dist-info/RECORD
