Metadata-Version: 2.1
Name: leo_data_analyser
Version: 1.0.0
Summary: Generate profile report for pandas DataFrame
Home-page: https://github.com/anthropoleo
Author: Leandro Falero
Author-email: leandroofalero@outlook.com
License: MIT
Keywords: pandas data-science data-analysis python jupyter ipython
Classifier: Development Status :: 5 - Production/Stable
Classifier: Topic :: Software Development :: Build Tools
Classifier: License :: OSI Approved :: MIT License
Classifier: Environment :: Console
Classifier: Operating System :: OS Independent
Classifier: Intended Audience :: Science/Research
Classifier: Intended Audience :: Developers
Classifier: Intended Audience :: Financial and Insurance Industry
Classifier: Intended Audience :: Healthcare Industry
Classifier: Topic :: Scientific/Engineering
Classifier: Framework :: IPython
Classifier: Programming Language :: Python :: 3
Classifier: Programming Language :: Python :: 3.7
Classifier: Programming Language :: Python :: 3.8
Classifier: Programming Language :: Python :: 3.9
Classifier: Programming Language :: Python :: 3.10
Classifier: Programming Language :: Python :: 3.11
Classifier: Programming Language :: Python :: 3.12
Requires-Python: >=3.7, <3.13
License-File: LICENSE
Requires-Dist: scipy<1.14,>=1.4.1
Requires-Dist: pandas!=1.4.0,<3,>1.1
Requires-Dist: matplotlib<3.10,>=3.5
Requires-Dist: pydantic>=2
Requires-Dist: PyYAML<6.1,>=5.0.0
Requires-Dist: jinja2<3.2,>=2.11.1
Requires-Dist: visions[type_image_path]<0.7.7,>=0.7.5
Requires-Dist: numpy<2,>=1.16.0
Requires-Dist: htmlmin==0.1.12
Requires-Dist: phik<0.13,>=0.11.1
Requires-Dist: requests<3,>=2.24.0
Requires-Dist: tqdm<5,>=4.48.2
Requires-Dist: seaborn<0.14,>=0.10.1
Requires-Dist: multimethod<2,>=1.4
Requires-Dist: statsmodels<1,>=0.13.2
Requires-Dist: typeguard<5,>=3
Requires-Dist: imagehash==4.3.1
Requires-Dist: wordcloud>=1.9.3
Requires-Dist: dacite>=1.8
Requires-Dist: numba<1,>=0.56.0
Provides-Extra: notebook
Requires-Dist: jupyter>=1.0.0; extra == "notebook"
Requires-Dist: ipywidgets>=7.5.1; extra == "notebook"
Provides-Extra: unicode
Requires-Dist: tangled-up-in-unicode==0.2.0; extra == "unicode"
